ribbet/__init__.py
ribbet/ribbet.py
ribbet/ribbet_cli.py
ribbet-0.1.4.dist-info/LICENSE
ribbet-0.1.4.dist-info/METADATA
ribbet-0.1.4.dist-info/WHEEL
ribbet-0.1.4.dist-info/entry_points.txt
ribbet-0.1.4.dist-info/top_level.txt
ribbet-0.1.4.dist-info/RECORD
