Metadata-Version: 2.1
Name: ribbet
Version: 0.1.4
Summary: Ribbet is a package that introduces users to Ribbet the frog, a virtual pet that cheers up the user based on different commands. Let's eat bugs together!
Author: Christina Borao, Bonny Chavarría, Damla Önder, Yura Wu
License: GNU GENERAL PUBLIC LICENSE
Project-URL: Homepage, https://github.com/software-students-spring2024/3-python-package-exercise-berries
Project-URL: Repository, https://github.com/software-students-spring2024/3-python-package-exercise-berries.git
Project-URL: Bug Tracker, https://github.com/software-students-spring2024/3-python-package-exercise-berries/issues
Keywords: python,package,build,frog,encourage,animals,cute,funny,bugs
Classifier: Development Status :: 5 - Production/Stable
Classifier: Programming Language :: Python :: 3
Requires-Python: >=3.11
License-File: LICENSE
Requires-Dist: argparse <2.0.0,>=1.4.0
Requires-Dist: pytest ~=8.1.1
Requires-Dist: build <2.0.0,>=1.1.1
